{
  "posts": [
    {
      "id": 1,
      "title": "json-server",
      "author": "typicode"
    }
  ],
  "comments": [
    {
      "id": 1,
      "body": "some comment",
      "postId": 1
    }
  ],
  "profile": {
    "name": "typicode"
  },
  "todo": [
    {
      "completed": true,
      "title": "www 12345",
      "id": 13,
      "edit": false
    },
    {
      "completed": true,
      "title": "www",
      "id": 14
    },
    {
      "completed": true,
      "title": "qweqweqxqxqxq",
      "id": 15
    },
    {
      "completed": true,
      "title": "testando",
      "id": 16
    },
    {
      "completed": false,
      "title": "ooooo",
      "id": 18
    },
    {
      "completed": true,
      "title": "iiiiooo",
      "id": 19
    }
  ]
}